{
  "project_info": {
    "project_number": "969057077311",
    "project_id": "wiki-now2",
    "storage_bucket": "wiki-now2.firebasestorage.app"
  },
  "client": [
    {
      "client_info": {
        "mobilesdk_app_id": "1:969057077311:android:cc663412196804c055d08a",
        "android_client_info": {
          "package_name": "com.example.wikinow"
        }
      },
      "oauth_client": [],
      "api_key": [
        {
          "current_key": "AIzaSyAO0wE-i3yMIY1evGA7tu0Oe4jIXBOpLH0"
        }
      ],
      "services": {
        "appinvite_service": {
          "other_platform_oauth_client": []
        }
      }
    }
  ],
  "configuration_version": "1"
}